bibster/__init__.py
bibster/admin_urls.py
bibster/apps.py
bibster/auto_fill.py
bibster/auxiliaries.py
bibster/block_auxiliaries.py
bibster/blocks.py
bibster/content_admin.py
bibster/default_settings.py
bibster/format_auxiliaries.py
bibster/frontend.py
bibster/harvard_style.py
bibster/html_markup.py
bibster/identifiers.py
bibster/mixins.py
bibster/model_admin.py
bibster/model_porter.py
bibster/models.py
bibster/permissions.py
bibster/plain_name_format.py
bibster/wagtail_hooks.py
bibster/xml_io.py
bibster/formatting/__init__.py
bibster/formatting/base.py
bibster/formatting/dictionary_format.py
bibster/formatting/ellipsis.py
bibster/formatting/grouping_format.py
bibster/formatting/markup.py
bibster/formatting/predicate_format.py
bibster/formatting/sequence_format.py
bibster/formatting/sequence_map.py
bibster/formatting/switch_format.py
bibster/formatting/titlecase.py
bibster/formatting/value_converters.py
bibster/formatting/value_format.py
bibster/formatting/xml_io.py
bibster/migrations/0001_initial.py
bibster/migrations/__init__.py
bibster/static/bibster/css/bibster.css
bibster/static/bibster/js/publication_modeladmin.js
bibster/static/bibster/js/reference_block.js
bibster/static/bibster/js/reference_lookup.js
bibster/templates/bibster/blocks/publication_list.html
bibster/templates/bibster/blocks/publication_list_switch.html
bibster/templates/bibster/blocks/publication_showcase.html
bibster/templates/bibster/blocks/publication_showcase_switch.html
bibster/templates/bibster/blocks/reference_block.html
bibster/templates/modeladmin/bibster/publication/index.html
bibster/templatetags/__init__.py
bibster/templatetags/bibster_tags.py
bibster/views/__init__.py
bibster/views/action.py
bibster/views/lookup.py
bibster-4.1.1.dist-info/AUTHORS.txt
bibster-4.1.1.dist-info/LICENSE.txt
bibster-4.1.1.dist-info/METADATA
bibster-4.1.1.dist-info/WHEEL
bibster-4.1.1.dist-info/top_level.txt
bibster-4.1.1.dist-info/RECORD
